netix/__init__.py
netix/__main__.py
netix/asgi_lifespan.py
netix/asgi_server.py
netix/daemon.py
netix/exceptions.py
netix/handlers.py
netix/http_server.py
netix/monitor.py
netix/script.py
netix/server.py
netix/utils.py
netix/lib/__init__.py
netix/lib/__queue.py
netix/lib/_content.py
netix/lib/connections.py
netix/lib/contexts.py
netix/lib/http_exception.py
netix/lib/http_protocol.py
netix/lib/http_request.py
netix/lib/http_response.py
netix/lib/locks.py
netix/lib/pools.py
netix/lib/request.py
netix/lib/response.py
netix/lib/tasks.py
netix/lib/websocket.py
netix/lib/h1parser/__init__.py
netix/lib/h1parser/parse_header.py
netix-1.13.dist-info/LICENSE
netix-1.13.dist-info/METADATA
netix-1.13.dist-info/WHEEL
netix-1.13.dist-info/entry_points.txt
netix-1.13.dist-info/top_level.txt
netix-1.13.dist-info/RECORD
