Metadata-Version: 2.1
Name: netix
Version: 1.13
Summary: Netix is a high-performance ASGI (Asynchronous Server Gateway Interface) server designed for efficiently serving ASGI web applications and APIs. It offers a robust, customizable, and easy-to-use platform for deploying your ASGI applications.
Home-page: https://github.com/embrake/netix/
Author: Pawan kumar
Author-email: embrakeproject@gmail.com
License: MIT
Keywords: ASGI Server user-friendly high concurrancy
Platform: UNKNOWN
Classifier: Development Status :: 5 - Production/Stable
Classifier: License :: OSI Approved :: MIT License
Classifier: Programming Language :: Python :: 3
Classifier: Programming Language :: Python :: 3.6
Classifier: Programming Language :: Python :: 3.7
Classifier: Programming Language :: Python :: 3.8
Classifier: Programming Language :: Python :: 3.9
License-File: LICENSE
Requires-Dist: psutil
Requires-Dist: schedule
